f1-cli/__init__.py
f1_cli-0.0.1.data/scripts/f1
tests/__init__.py
tests/integration/__init__.py
tests/unit/__init__.py
f1_cli-0.0.1.dist-info/LICENSE
f1_cli-0.0.1.dist-info/METADATA
f1_cli-0.0.1.dist-info/WHEEL
f1_cli-0.0.1.dist-info/top_level.txt
f1_cli-0.0.1.dist-info/RECORD
